KratosMultiphysics/SystemIdentificationApplication/__init__.py
KratosMultiphysics/SystemIdentificationApplication/python_registry_lists.py
KratosMultiphysics/SystemIdentificationApplication/sensor_generator_analysis.py
KratosMultiphysics/SystemIdentificationApplication/controls/data_values_control.py
KratosMultiphysics/SystemIdentificationApplication/controls/material_properties_control.py
KratosMultiphysics/SystemIdentificationApplication/processes/sensor_output_process.py
KratosMultiphysics/SystemIdentificationApplication/responses/damage_detection_response.py
KratosMultiphysics/SystemIdentificationApplication/responses/pressure_detection_response.py
KratosMultiphysics/SystemIdentificationApplication/responses/temperature_detection_response.py
KratosMultiphysics/SystemIdentificationApplication/sensor_io/sensor_model_part_controller.py
KratosMultiphysics/SystemIdentificationApplication/sensor_sensitivity_solvers/response_sensitivity_analysis.py
KratosMultiphysics/SystemIdentificationApplication/sensor_sensitivity_solvers/response_sensitivity_interface.py
KratosMultiphysics/SystemIdentificationApplication/sensor_sensitivity_solvers/sensor_sensitivity_adjoint_static_solver.py
KratosMultiphysics/SystemIdentificationApplication/sensor_sensitivity_solvers/system_identification_static_analysis.py
KratosMultiphysics/SystemIdentificationApplication/utilities/data_utils.py
KratosMultiphysics/SystemIdentificationApplication/utilities/expression_utils.py
KratosMultiphysics/SystemIdentificationApplication/utilities/sensor_utils.py
KratosMultiphysics/.libs/KratosSystemIdentificationApplication.pyd
KratosMultiphysics/.libs/KratosSystemIdentificationCore.dll
KratosMultiphysics/.libs/KratosSystemIdentificationCore.lib
kratossystemidentificationapplication-10.4.0.dist-info/METADATA
kratossystemidentificationapplication-10.4.0.dist-info/WHEEL
kratossystemidentificationapplication-10.4.0.dist-info/RECORD
